spread_spectrum.v
/* This module is built for functions that can be 
* expressed using the `define feature in verilog */

`define channel_capacity(W, N, S) W*$ln(1+S/N)

channel_capacity.v
//Module Name: channel_capacity
//this displays the relationship between the ability of a channel to transfer
//error-free information, compared with the signal to noise ratio existing in
//the channel, and the bandwidth used to transmit the information
//function: channel capacity
//W = bandwidth(in hz) 
//C = capacity in bits/sec
//N = noise power
//S = signal power
//`define channel_capacity(W, N, S) W*$ln(1+S/N)

module channel_capacity(
	input real W,
	input real N,
	input real S,
	output real C
);

assign C = W*clogb2(1+S/N);
//always @(W,N,S,C)
//define the clogb2 function
function integer clogb2;
	input integer value;
	begin
		//value = value - 1; not neccessary 
		for(clogb2 = 0; value > 0; clogb2 = clogb2 + 1)
			value = value >> 1;
	end
endfunction
endmodule

gain_advantage.v
//Module Name: gain)_advantage:

//calculates the gain advantage fomr the deviation ratio,
//and the the signal to noise ratio
//
`define process_gain(beta,signal,noise) 3*beta*beta*(signal/noise)
module gain_advantage(
	input real beta,
	input real signal,
	input real noise,
	output real out
);
assign out = 3*beta*beta*signal/noise;
endmodule

autocorrelation.v
`timescale 1ns/1ps
//We are performing autocorrelation across 2 signals: 
//We will do this by multiplying at discrete points
//multiplying (easy way out ) 

module autocorrelation#(parameter WIDTH = 256,
						parameter C_WIDTH = 8)(
	input clk,
	input reset,
	input logic [C_WIDTH-1:0]count,
	input logic [WIDTH-1:0] signal_1,
	input logic [WIDTH-1:0] signal_2,
	output  [WIDTH-1:0] out
);
	integer a, tmp;
	assign out[WIDTH-1:0] = tmp;
	always @(posedge clk) begin
		a = 0;
		tmp = 0;
		//$display("signal1 and signal2 are %b and %b\n", signal_1, signal_2);
		for(a = 0; a < WIDTH; a=a+1)
			if(count - a >= 0 && count - a < WIDTH)begin
				tmp = tmp+ signal_1[a +:1];//signal_1[a]*signal_2[count - a];
				//$display("count - a = %d", count-a);
				//$display("the result for this convoluation is %d \n", tmp);
			end
		$display("the result for this convoluation is %d \n", tmp);
	end
endmodule

counter.v
module counter#(parameter WIDTH = 8)(
	input clk,
	input reset,
	input enable,
	output logic [WIDTH-1:0] count
);
	//input enable, clk, reset;
	//output reg[WIDTH-1:0] count;
	//output reg[WIDTH-1:0] count;

	always @(posedge clk) begin
		if(reset) begin
//			$display("count is %d \n", count);
			count <= 8'b0;
		end else if(enable) begin
			if (^count === 1'bx) begin
				count = 1'b0;
			end
			count = count + 1;
			//$display("count is %d \n", count);
		end
	end

endmodule

tb_top.v
`include "channel_capacity.v"
`include "gain_advantage.v"
`include "spread_spectrum.v"
`include "autocorrelation.v"
`include "counter.v"
module tb_top;
	reg clk, reset, enable;
	wire[7:0] count; 
	//integer count;

	counter #(8)cnt(
				.clk(clk),
				.reset(reset),
				.enable(enable),
				.count(count)
	);

	wire real out, out2;

	//FOR AUTOCORRELATION TB
	parameter SIZE = 256;
	integer max_position, max, i, con_counter;
	wire[SIZE-1:0] s1, s2, s3, tmp;
	integer con_out[SIZE-1:0];

	//Whenever count increases, get con_out
	always #5 begin
		con_out[count] = s3;
	end

	assign tmp = {SIZE{1'b1}};
	assign s1 = {SIZE{1'b1}};
	assign s2 = {SIZE{1'b1}};
	//assign s1 = {tmp[127:0], 128'b0};//{512{1'b1}};
	//assign s2 = {tmp[127:0], 128'b0};//{512{1'b1}};
//	assign s2 = {64'b0, tmp[127:0], 192'b0};//{512{1'b1}};
	///////////////////////////////////////
	
	initial begin
		clk = 0;
		reset = 0;
		enable=1;
		for(con_counter = 0; con_counter < SIZE; con_counter=con_counter+1)
			con_out[con_counter] = 0;
	end

	initial begin
		$dumpfile("counter.vcd");
		$dumpvars;
	end

	always
	begin
		#5 clk = !clk;
	end

	initial begin
		#2555
		$display("The gain advantage of our sample is %f \n", out);
		$display("The channel capacity of our sample is %f \n",out2);
		$display("The channel capacity to Bandwidth ratio is is %f \n",`channel_capacity(1.4,5.666,1));
		max_position = 0;
		for(i = 0; i < SIZE; i=i+1)
			if(con_out[max_position] < con_out[i])
				max_position = i; 
		$display("for auto correlation, the position N where it seems",
				" to be correlated perfectly is at position %d with a ", max_position,
				"score %d\n", con_out[max_position]);
		$finish;
	end

	autocorrelation #(SIZE, 8) ac (
							.clk(clk), 
							.reset(reset), 
							.count(count),
							.signal_1(s1), 
							.signal_2(s2), 
							.out(s3)
							);	

	gain_advantage ga(
					.beta(0.132), 
					.signal(1), 
					.noise(1), 
					.out(out)
					);

	channel_capacity cc(
					.W(1.0), 
					.N(1.0), 
					.S(31.0), 
					.C(out2)
					);

endmodule

counter.vcd
$date
	Wed Jun 20 02:37:21 2018
$end
$version
	Icarus Verilog
$end
$timescale
	1ps
$end
$scope module tb_top $end
$var wire 256 ! s1 [255:0] $end
$var wire 256 " s2 [255:0] $end
$var wire 256 # tmp [255:0] $end
$var wire 256 $ s3 [255:0] $end
$var wire 8 % count [7:0] $end
$var reg 1 & clk $end
$var reg 1 ' enable $end
$var reg 1 ( reset $end
$var integer 32 ) con_counter [31:0] $end
$var integer 32 * i [31:0] $end
$var integer 32 + max_position [31:0] $end
$var real 1 , out2 $end
$var real 1 - out $end
$scope module ac $end
$var wire 1 & clk $end
$var wire 1 ( reset $end
$var wire 256 . signal_1 [255:0] $end
$var wire 256 / signal_2 [255:0] $end
$var wire 256 0 out [255:0] $end
$var wire 8 1 count [7:0] $end
$var integer 32 2 a [31:0] $end
$var integer 32 3 tmp [31:0] $end
$upscope $end
$scope module cc $end
$var real 1 4 N $end
$var real 1 5 S $end
$var real 1 6 W $end
$var real 1 7 C $end
$scope function clogb2 $end
$var integer 32 8 clogb2 [31:0] $end
$var integer 32 9 value [31:0] $end
$upscope $end
$upscope $end
$scope module cnt $end
$var wire 1 & clk $end
$var wire 1 ' enable $end
$var wire 1 ( reset $end
$var reg 8 : count [7:0] $end
$upscope $end
$scope module ga $end
$var real 1 ; beta $end
$var real 1 < noise $end
$var real 1 = signal $end
$var real 1 > out $end
$upscope $end
$upscope $end
$enddefinitions $end
#0
$dumpvars
r0.05227200000000001 >
r1 =
r1 <
r0.132 ;
bx :
b0 9
b110 8
r6 7
r1 6
r31 5
r1 4
bx 3
bx 2
bx 1
bx 0
b1111111111111111111111111111111111111111111111111111111111111111111111111111111111111111111111111111111111111111111111111111111111111111111111111111111111111111111111111111111111111111111111111111111111111111111111111111111111111111111111111111111111111111 /
b1111111111111111111111111111111111111111111111111111111111111111111111111111111111111111111111111111111111111111111111111111111111111111111111111111111111111111111111111111111111111111111111111111111111111111111111111111111111111111111111111111111111111111 .
r0.05227200000000001 -
r6 ,
bx +
bx *
b100000000 )
0(
1'
0&
bx %
bx $
b1111111111111111111111111111111111111111111111111111111111111111111111111111111111111111111111111111111111111111111111111111111111111111111111111111111111111111111111111111111111111111111111111111111111111111111111111111111111111111111111111111111111111111 #
b1111111111111111111111111111111111111111111111111111111111111111111111111111111111111111111111111111111111111111111111111111111111111111111111111111111111111111111111111111111111111111111111111111111111111111111111111111111111111111111111111111111111111111 "
b1111111111111111111111111111111111111111111111111111111111111111111111111111111111111111111111111111111111111111111111111111111111111111111111111111111111111111111111111111111111111111111111111111111111111111111111111111111111111111111111111111111111111111 !
$end
#5000
b1 %
b1 1
b1 :
b0 $
b0 0
b0 3
b100000000 2
1&
#10000
0&
#15000
b11 $
b11 0
b11 3
b100000000 2
b10 %
b10 1
b10 :
1&
#20000
0&
#25000
b11 %
b11 1
b11 :
b11 $
b11 0
b11 3
b100000000 2
1&
#30000
0&
#35000
b101 $
b101 0
b101 3
b100000000 2
b100 %
b100 1
b100 :
1&
#40000
0&
#45000
b101 %
b101 1
b101 :
b101 $
b101 0
b101 3
b100000000 2
1&
#50000
0&
#55000
b111 $
b111 0
b111 3
b100000000 2
b110 %
b110 1
b110 :
1&
#60000
0&
#65000
b111 %
b111 1
b111 :
b111 $
b111 0
b111 3
b100000000 2
1&
#70000
0&
#75000
b1001 $
b1001 0
b1001 3
b100000000 2
b1000 %
b1000 1
b1000 :
1&
#80000
0&
#85000
b1001 %
b1001 1
b1001 :
b1001 $
b1001 0
b1001 3
b100000000 2
1&
#90000
0&
#95000
b1011 $
b1011 0
b1011 3
b100000000 2
b1010 %
b1010 1
b1010 :
1&
#100000
0&
#105000
b1011 %
b1011 1
b1011 :
b1011 $
b1011 0
b1011 3
b100000000 2
1&
#110000
0&
#115000
b1101 $
b1101 0
b1101 3
b100000000 2
b1100 %
b1100 1
b1100 :
1&
#120000
0&
#125000
b1101 %
b1101 1
b1101 :
b1101 $
b1101 0
b1101 3
b100000000 2
1&
#130000
0&
#135000
b1111 $
b1111 0
b1111 3
b100000000 2
b1110 %
b1110 1
b1110 :
1&
#140000
0&
#145000
b1111 %
b1111 1
b1111 :
b1111 $
b1111 0
b1111 3
b100000000 2
1&
#150000
0&
#155000
b10001 $
b10001 0
b10001 3
b100000000 2
b10000 %
b10000 1
b10000 :
1&
#160000
0&
#165000
b10001 %
b10001 1
b10001 :
b10001 $
b10001 0
b10001 3
b100000000 2
1&
#170000
0&
#175000
b10011 $
b10011 0
b10011 3
b100000000 2
b10010 %
b10010 1
b10010 :
1&
#180000
0&
#185000
b10011 %
b10011 1
b10011 :
b10011 $
b10011 0
b10011 3
b100000000 2
1&
#190000
0&
#195000
b10101 $
b10101 0
b10101 3
b100000000 2
b10100 %
b10100 1
b10100 :
1&
#200000
0&
#205000
b10101 %
b10101 1
b10101 :
b10101 $
b10101 0
b10101 3
b100000000 2
1&
#210000
0&
#215000
b10111 $
b10111 0
b10111 3
b100000000 2
b10110 %
b10110 1
b10110 :
1&
#220000
0&
#225000
b10111 %
b10111 1
b10111 :
b10111 $
b10111 0
b10111 3
b100000000 2
1&
#230000
0&
#235000
b11001 $
b11001 0
b11001 3
b100000000 2
b11000 %
b11000 1
b11000 :
1&
#240000
0&
#245000
b11001 %
b11001 1
b11001 :
b11001 $
b11001 0
b11001 3
b100000000 2
1&
#250000
0&
#255000
b11011 $
b11011 0
b11011 3
b100000000 2
b11010 %
b11010 1
b11010 :
1&
#260000
0&
#265000
b11011 %
b11011 1
b11011 :
b11011 $
b11011 0
b11011 3
b100000000 2
1&
#270000
0&
#275000
b11101 $
b11101 0
b11101 3
b100000000 2
b11100 %
b11100 1
b11100 :
1&
#280000
0&
#285000
b11101 %
b11101 1
b11101 :
b11101 $
b11101 0
b11101 3
b100000000 2
1&
#290000
0&
#295000
b11111 $
b11111 0
b11111 3
b100000000 2
b11110 %
b11110 1
b11110 :
1&
#300000
0&
#305000
b11111 %
b11111 1
b11111 :
b11111 $
b11111 0
b11111 3
b100000000 2
1&
#310000
0&
#315000
b100001 $
b100001 0
b100001 3
b100000000 2
b100000 %
b100000 1
b100000 :
1&
#320000
0&
#325000
b100001 %
b100001 1
b100001 :
b100001 $
b100001 0
b100001 3
b100000000 2
1&
#330000
0&
#335000
b100011 $
b100011 0
b100011 3
b100000000 2
b100010 %
b100010 1
b100010 :
1&
#340000
0&
#345000
b100011 %
b100011 1
b100011 :
b100011 $
b100011 0
b100011 3
b100000000 2
1&
#350000
0&
#355000
b100101 $
b100101 0
b100101 3
b100000000 2
b100100 %
b100100 1
b100100 :
1&
#360000
0&
#365000
b100101 %
b100101 1
b100101 :
b100101 $
b100101 0
b100101 3
b100000000 2
1&
#370000
0&
#375000
b100111 $
b100111 0
b100111 3
b100000000 2
b100110 %
b100110 1
b100110 :
1&
#380000
0&
#385000
b100111 %
b100111 1
b100111 :
b100111 $
b100111 0
b100111 3
b100000000 2
1&
#390000
0&
#395000
b101001 $
b101001 0
b101001 3
b100000000 2
b101000 %
b101000 1
b101000 :
1&
#400000
0&
#405000
b101001 %
b101001 1
b101001 :
b101001 $
b101001 0
b101001 3
b100000000 2
1&
#410000
0&
#415000
b101011 $
b101011 0
b101011 3
b100000000 2
b101010 %
b101010 1
b101010 :
1&
#420000
0&
#425000
b101011 %
b101011 1
b101011 :
b101011 $
b101011 0
b101011 3
b100000000 2
1&
#430000
0&
#435000
b101101 $
b101101 0
b101101 3
b100000000 2
b101100 %
b101100 1
b101100 :
1&
#440000
0&
#445000
b101101 %
b101101 1
b101101 :
b101101 $
b101101 0
b101101 3
b100000000 2
1&
#450000
0&
#455000
b101111 $
b101111 0
b101111 3
b100000000 2
b101110 %
b101110 1
b101110 :
1&
#460000
0&
#465000
b101111 %
b101111 1
b101111 :
b101111 $
b101111 0
b101111 3
b100000000 2
1&
#470000
0&
#475000
b110001 $
b110001 0
b110001 3
b100000000 2
b110000 %
b110000 1
b110000 :
1&
#480000
0&
#485000
b110001 %
b110001 1
b110001 :
b110001 $
b110001 0
b110001 3
b100000000 2
1&
#490000
0&
#495000
b110011 $
b110011 0
b110011 3
b100000000 2
b110010 %
b110010 1
b110010 :
1&
#500000
0&
#505000
b110011 %
b110011 1
b110011 :
b110011 $
b110011 0
b110011 3
b100000000 2
1&
#510000
0&
#515000
b110101 $
b110101 0
b110101 3
b100000000 2
b110100 %
b110100 1
b110100 :
1&
#520000
0&
#525000
b110101 %
b110101 1
b110101 :
b110101 $
b110101 0
b110101 3
b100000000 2
1&
#530000
0&
#535000
b110111 $
b110111 0
b110111 3
b100000000 2
b110110 %
b110110 1
b110110 :
1&
#540000
0&
#545000
b110111 %
b110111 1
b110111 :
b110111 $
b110111 0
b110111 3
b100000000 2
1&
#550000
0&
#555000
b111001 $
b111001 0
b111001 3
b100000000 2
b111000 %
b111000 1
b111000 :
1&
#560000
0&
#565000
b111001 %
b111001 1
b111001 :
b111001 $
b111001 0
b111001 3
b100000000 2
1&
#570000
0&
#575000
b111011 $
b111011 0
b111011 3
b100000000 2
b111010 %
b111010 1
b111010 :
1&
#580000
0&
#585000
b111011 %
b111011 1
b111011 :
b111011 $
b111011 0
b111011 3
b100000000 2
1&
#590000
0&
#595000
b111101 $
b111101 0
b111101 3
b100000000 2
b111100 %
b111100 1
b111100 :
1&
#600000
0&
#605000
b111101 %
b111101 1
b111101 :
b111101 $
b111101 0
b111101 3
b100000000 2
1&
#610000
0&
#615000
b111111 $
b111111 0
b111111 3
b100000000 2
b111110 %
b111110 1
b111110 :
1&
#620000
0&
#625000
b111111 %
b111111 1
b111111 :
b111111 $
b111111 0
b111111 3
b100000000 2
1&
#630000
0&
#635000
b1000001 $
b1000001 0
b1000001 3
b100000000 2
b1000000 %
b1000000 1
b1000000 :
1&
#640000
0&
#645000
b1000001 %
b1000001 1
b1000001 :
b1000001 $
b1000001 0
b1000001 3
b100000000 2
1&
#650000
0&
#655000
b1000011 $
b1000011 0
b1000011 3
b100000000 2
b1000010 %
b1000010 1
b1000010 :
1&
#660000
0&
#665000
b1000011 %
b1000011 1
b1000011 :
b1000011 $
b1000011 0
b1000011 3
b100000000 2
1&
#670000
0&
#675000
b1000101 $
b1000101 0
b1000101 3
b100000000 2
b1000100 %
b1000100 1
b1000100 :
1&
#680000
0&
#685000
b1000101 %
b1000101 1
b1000101 :
b1000101 $
b1000101 0
b1000101 3
b100000000 2
1&
#690000
0&
#695000
b1000111 $
b1000111 0
b1000111 3
b100000000 2
b1000110 %
b1000110 1
b1000110 :
1&
#700000
0&
#705000
b1000111 %
b1000111 1
b1000111 :
b1000111 $
b1000111 0
b1000111 3
b100000000 2
1&
#710000
0&
#715000
b1001001 $
b1001001 0
b1001001 3
b100000000 2
b1001000 %
b1001000 1
b1001000 :
1&
#720000
0&
#725000
b1001001 %
b1001001 1
b1001001 :
b1001001 $
b1001001 0
b1001001 3
b100000000 2
1&
#730000
0&
#735000
b1001011 $
b1001011 0
b1001011 3
b100000000 2
b1001010 %
b1001010 1
b1001010 :
1&
#740000
0&
#745000
b1001011 %
b1001011 1
b1001011 :
b1001011 $
b1001011 0
b1001011 3
b100000000 2
1&
#750000
0&
#755000
b1001101 $
b1001101 0
b1001101 3
b100000000 2
b1001100 %
b1001100 1
b1001100 :
1&
#760000
0&
#765000
b1001101 %
b1001101 1
b1001101 :
b1001101 $
b1001101 0
b1001101 3
b100000000 2
1&
#770000
0&
#775000
b1001111 $
b1001111 0
b1001111 3
b100000000 2
b1001110 %
b1001110 1
b1001110 :
1&
#780000
0&
#785000
b1001111 %
b1001111 1
b1001111 :
b1001111 $
b1001111 0
b1001111 3
b100000000 2
1&
#790000
0&
#795000
b1010001 $
b1010001 0
b1010001 3
b100000000 2
b1010000 %
b1010000 1
b1010000 :
1&
#800000
0&
#805000
b1010001 %
b1010001 1
b1010001 :
b1010001 $
b1010001 0
b1010001 3
b100000000 2
1&
#810000
0&
#815000
b1010011 $
b1010011 0
b1010011 3
b100000000 2
b1010010 %
b1010010 1
b1010010 :
1&
#820000
0&
#825000
b1010011 %
b1010011 1
b1010011 :
b1010011 $
b1010011 0
b1010011 3
b100000000 2
1&
#830000
0&
#835000
b1010101 $
b1010101 0
b1010101 3
b100000000 2
b1010100 %
b1010100 1
b1010100 :
1&
#840000
0&
#845000
b1010101 %
b1010101 1
b1010101 :
b1010101 $
b1010101 0
b1010101 3
b100000000 2
1&
#850000
0&
#855000
b1010111 $
b1010111 0
b1010111 3
b100000000 2
b1010110 %
b1010110 1
b1010110 :
1&
#860000
0&
#865000
b1010111 %
b1010111 1
b1010111 :
b1010111 $
b1010111 0
b1010111 3
b100000000 2
1&
#870000
0&
#875000
b1011001 $
b1011001 0
b1011001 3
b100000000 2
b1011000 %
b1011000 1
b1011000 :
1&
#880000
0&
#885000
b1011001 %
b1011001 1
b1011001 :
b1011001 $
b1011001 0
b1011001 3
b100000000 2
1&
#890000
0&
#895000
b1011011 $
b1011011 0
b1011011 3
b100000000 2
b1011010 %
b1011010 1
b1011010 :
1&
#900000
0&
#905000
b1011011 %
b1011011 1
b1011011 :
b1011011 $
b1011011 0
b1011011 3
b100000000 2
1&
#910000
0&
#915000
b1011101 $
b1011101 0
b1011101 3
b100000000 2
b1011100 %
b1011100 1
b1011100 :
1&
#920000
0&
#925000
b1011101 %
b1011101 1
b1011101 :
b1011101 $
b1011101 0
b1011101 3
b100000000 2
1&
#930000
0&
#935000
b1011111 $
b1011111 0
b1011111 3
b100000000 2
b1011110 %
b1011110 1
b1011110 :
1&
#940000
0&
#945000
b1011111 %
b1011111 1
b1011111 :
b1011111 $
b1011111 0
b1011111 3
b100000000 2
1&
#950000
0&
#955000
b1100001 $
b1100001 0
b1100001 3
b100000000 2
b1100000 %
b1100000 1
b1100000 :
1&
#960000
0&
#965000
b1100001 %
b1100001 1
b1100001 :
b1100001 $
b1100001 0
b1100001 3
b100000000 2
1&
#970000
0&
#975000
b1100011 $
b1100011 0
b1100011 3
b100000000 2
b1100010 %
b1100010 1
b1100010 :
1&
#980000
0&
#985000
b1100011 %
b1100011 1
b1100011 :
b1100011 $
b1100011 0
b1100011 3
b100000000 2
1&
#990000
0&
#995000
b1100101 $
b1100101 0
b1100101 3
b100000000 2
b1100100 %
b1100100 1
b1100100 :
1&
#1000000
0&
#1005000
b1100101 %
b1100101 1
b1100101 :
b1100101 $
b1100101 0
b1100101 3
b100000000 2
1&
#1010000
0&
#1015000
b1100111 $
b1100111 0
b1100111 3
b100000000 2
b1100110 %
b1100110 1
b1100110 :
1&
#1020000
0&
#1025000
b1100111 %
b1100111 1
b1100111 :
b1100111 $
b1100111 0
b1100111 3
b100000000 2
1&
#1030000
0&
#1035000
b1101001 $
b1101001 0
b1101001 3
b100000000 2
b1101000 %
b1101000 1
b1101000 :
1&
#1040000
0&
#1045000
b1101001 %
b1101001 1
b1101001 :
b1101001 $
b1101001 0
b1101001 3
b100000000 2
1&
#1050000
0&
#1055000
b1101011 $
b1101011 0
b1101011 3
b100000000 2
b1101010 %
b1101010 1
b1101010 :
1&
#1060000
0&
#1065000
b1101011 %
b1101011 1
b1101011 :
b1101011 $
b1101011 0
b1101011 3
b100000000 2
1&
#1070000
0&
#1075000
b1101101 $
b1101101 0
b1101101 3
b100000000 2
b1101100 %
b1101100 1
b1101100 :
1&
#1080000
0&
#1085000
b1101101 %
b1101101 1
b1101101 :
b1101101 $
b1101101 0
b1101101 3
b100000000 2
1&
#1090000
0&
#1095000
b1101111 $
b1101111 0
b1101111 3
b100000000 2
b1101110 %
b1101110 1
b1101110 :
1&
#1100000
0&
#1105000
b1101111 %
b1101111 1
b1101111 :
b1101111 $
b1101111 0
b1101111 3
b100000000 2
1&
#1110000
0&
#1115000
b1110001 $
b1110001 0
b1110001 3
b100000000 2
b1110000 %
b1110000 1
b1110000 :
1&
#1120000
0&
#1125000
b1110001 %
b1110001 1
b1110001 :
b1110001 $
b1110001 0
b1110001 3
b100000000 2
1&
#1130000
0&
#1135000
b1110011 $
b1110011 0
b1110011 3
b100000000 2
b1110010 %
b1110010 1
b1110010 :
1&
#1140000
0&
#1145000
b1110011 %
b1110011 1
b1110011 :
b1110011 $
b1110011 0
b1110011 3
b100000000 2
1&
#1150000
0&
#1155000
b1110101 $
b1110101 0
b1110101 3
b100000000 2
b1110100 %
b1110100 1
b1110100 :
1&
#1160000
0&
#1165000
b1110101 %
b1110101 1
b1110101 :
b1110101 $
b1110101 0
b1110101 3
b100000000 2
1&
#1170000
0&
#1175000
b1110111 $
b1110111 0
b1110111 3
b100000000 2
b1110110 %
b1110110 1
b1110110 :
1&
#1180000
0&
#1185000
b1110111 %
b1110111 1
b1110111 :
b1110111 $
b1110111 0
b1110111 3
b100000000 2
1&
#1190000
0&
#1195000
b1111001 $
b1111001 0
b1111001 3
b100000000 2
b1111000 %
b1111000 1
b1111000 :
1&
#1200000
0&
#1205000
b1111001 %
b1111001 1
b1111001 :
b1111001 $
b1111001 0
b1111001 3
b100000000 2
1&
#1210000
0&
#1215000
b1111011 $
b1111011 0
b1111011 3
b100000000 2
b1111010 %
b1111010 1
b1111010 :
1&
#1220000
0&
#1225000
b1111011 %
b1111011 1
b1111011 :
b1111011 $
b1111011 0
b1111011 3
b100000000 2
1&
#1230000
0&
#1235000
b1111101 $
b1111101 0
b1111101 3
b100000000 2
b1111100 %
b1111100 1
b1111100 :
1&
#1240000
0&
#1245000
b1111101 %
b1111101 1
b1111101 :
b1111101 $
b1111101 0
b1111101 3
b100000000 2
1&
#1250000
0&
#1255000
b1111111 $
b1111111 0
b1111111 3
b100000000 2
b1111110 %
b1111110 1
b1111110 :
1&
#1260000
0&
#1265000
b1111111 %
b1111111 1
b1111111 :
b1111111 $
b1111111 0
b1111111 3
b100000000 2
1&
#1270000
0&
#1275000
b10000001 $
b10000001 0
b10000001 3
b100000000 2
b10000000 %
b10000000 1
b10000000 :
1&
#1280000
0&
#1285000
b10000001 %
b10000001 1
b10000001 :
b10000001 $
b10000001 0
b10000001 3
b100000000 2
1&
#1290000
0&
#1295000
b10000011 $
b10000011 0
b10000011 3
b100000000 2
b10000010 %
b10000010 1
b10000010 :
1&
#1300000
0&
#1305000
b10000011 %
b10000011 1
b10000011 :
b10000011 $
b10000011 0
b10000011 3
b100000000 2
1&
#1310000
0&
#1315000
b10000101 $
b10000101 0
b10000101 3
b100000000 2
b10000100 %
b10000100 1
b10000100 :
1&
#1320000
0&
#1325000
b10000101 %
b10000101 1
b10000101 :
b10000101 $
b10000101 0
b10000101 3
b100000000 2
1&
#1330000
0&
#1335000
b10000111 $
b10000111 0
b10000111 3
b100000000 2
b10000110 %
b10000110 1
b10000110 :
1&
#1340000
0&
#1345000
b10000111 %
b10000111 1
b10000111 :
b10000111 $
b10000111 0
b10000111 3
b100000000 2
1&
#1350000
0&
#1355000
b10001001 $
b10001001 0
b10001001 3
b100000000 2
b10001000 %
b10001000 1
b10001000 :
1&
#1360000
0&
#1365000
b10001001 %
b10001001 1
b10001001 :
b10001001 $
b10001001 0
b10001001 3
b100000000 2
1&
#1370000
0&
#1375000
b10001011 $
b10001011 0
b10001011 3
b100000000 2
b10001010 %
b10001010 1
b10001010 :
1&
#1380000
0&
#1385000
b10001011 %
b10001011 1
b10001011 :
b10001011 $
b10001011 0
b10001011 3
b100000000 2
1&
#1390000
0&
#1395000
b10001101 $
b10001101 0
b10001101 3
b100000000 2
b10001100 %
b10001100 1
b10001100 :
1&
#1400000
0&
#1405000
b10001101 %
b10001101 1
b10001101 :
b10001101 $
b10001101 0
b10001101 3
b100000000 2
1&
#1410000
0&
#1415000
b10001111 $
b10001111 0
b10001111 3
b100000000 2
b10001110 %
b10001110 1
b10001110 :
1&
#1420000
0&
#1425000
b10001111 %
b10001111 1
b10001111 :
b10001111 $
b10001111 0
b10001111 3
b100000000 2
1&
#1430000
0&
#1435000
b10010001 $
b10010001 0
b10010001 3
b100000000 2
b10010000 %
b10010000 1
b10010000 :
1&
#1440000
0&
#1445000
b10010001 %
b10010001 1
b10010001 :
b10010001 $
b10010001 0
b10010001 3
b100000000 2
1&
#1450000
0&
#1455000
b10010011 $
b10010011 0
b10010011 3
b100000000 2
b10010010 %
b10010010 1
b10010010 :
1&
#1460000
0&
#1465000
b10010011 %
b10010011 1
b10010011 :
b10010011 $
b10010011 0
b10010011 3
b100000000 2
1&
#1470000
0&
#1475000
b10010101 $
b10010101 0
b10010101 3
b100000000 2
b10010100 %
b10010100 1
b10010100 :
1&
#1480000
0&
#1485000
b10010101 %
b10010101 1
b10010101 :
b10010101 $
b10010101 0
b10010101 3
b100000000 2
1&
#1490000
0&
#1495000
b10010111 $
b10010111 0
b10010111 3
b100000000 2
b10010110 %
b10010110 1
b10010110 :
1&
#1500000
0&
#1505000
b10010111 %
b10010111 1
b10010111 :
b10010111 $
b10010111 0
b10010111 3
b100000000 2
1&
#1510000
0&
#1515000
b10011001 $
b10011001 0
b10011001 3
b100000000 2
b10011000 %
b10011000 1
b10011000 :
1&
#1520000
0&
#1525000
b10011001 %
b10011001 1
b10011001 :
b10011001 $
b10011001 0
b10011001 3
b100000000 2
1&
#1530000
0&
#1535000
b10011011 $
b10011011 0
b10011011 3
b100000000 2
b10011010 %
b10011010 1
b10011010 :
1&
#1540000
0&
#1545000
b10011011 %
b10011011 1
b10011011 :
b10011011 $
b10011011 0
b10011011 3
b100000000 2
1&
#1550000
0&
#1555000
b10011101 $
b10011101 0
b10011101 3
b100000000 2
b10011100 %
b10011100 1
b10011100 :
1&
#1560000
0&
#1565000
b10011101 %
b10011101 1
b10011101 :
b10011101 $
b10011101 0
b10011101 3
b100000000 2
1&
#1570000
0&
#1575000
b10011111 $
b10011111 0
b10011111 3
b100000000 2
b10011110 %
b10011110 1
b10011110 :
1&
#1580000
0&
#1585000
b10011111 %
b10011111 1
b10011111 :
b10011111 $
b10011111 0
b10011111 3
b100000000 2
1&
#1590000
0&
#1595000
b10100001 $
b10100001 0
b10100001 3
b100000000 2
b10100000 %
b10100000 1
b10100000 :
1&
#1600000
0&
#1605000
b10100001 %
b10100001 1
b10100001 :
b10100001 $
b10100001 0
b10100001 3
b100000000 2
1&
#1610000
0&
#1615000
b10100011 $
b10100011 0
b10100011 3
b100000000 2
b10100010 %
b10100010 1
b10100010 :
1&
#1620000
0&
#1625000
b10100011 %
b10100011 1
b10100011 :
b10100011 $
b10100011 0
b10100011 3
b100000000 2
1&
#1630000
0&
#1635000
b10100101 $
b10100101 0
b10100101 3
b100000000 2
b10100100 %
b10100100 1
b10100100 :
1&
#1640000
0&
#1645000
b10100101 %
b10100101 1
b10100101 :
b10100101 $
b10100101 0
b10100101 3
b100000000 2
1&
#1650000
0&
#1655000
b10100111 $
b10100111 0
b10100111 3
b100000000 2
b10100110 %
b10100110 1
b10100110 :
1&
#1660000
0&
#1665000
b10100111 %
b10100111 1
b10100111 :
b10100111 $
b10100111 0
b10100111 3
b100000000 2
1&
#1670000
0&
#1675000
b10101001 $
b10101001 0
b10101001 3
b100000000 2
b10101000 %
b10101000 1
b10101000 :
1&
#1680000
0&
#1685000
b10101001 %
b10101001 1
b10101001 :
b10101001 $
b10101001 0
b10101001 3
b100000000 2
1&
#1690000
0&
#1695000
b10101011 $
b10101011 0
b10101011 3
b100000000 2
b10101010 %
b10101010 1
b10101010 :
1&
#1700000
0&
#1705000
b10101011 %
b10101011 1
b10101011 :
b10101011 $
b10101011 0
b10101011 3
b100000000 2
1&
#1710000
0&
#1715000
b10101101 $
b10101101 0
b10101101 3
b100000000 2
b10101100 %
b10101100 1
b10101100 :
1&
#1720000
0&
#1725000
b10101101 %
b10101101 1
b10101101 :
b10101101 $
b10101101 0
b10101101 3
b100000000 2
1&
#1730000
0&
#1735000
b10101111 $
b10101111 0
b10101111 3
b100000000 2
b10101110 %
b10101110 1
b10101110 :
1&
#1740000
0&
#1745000
b10101111 %
b10101111 1
b10101111 :
b10101111 $
b10101111 0
b10101111 3
b100000000 2
1&
#1750000
0&
#1755000
b10110001 $
b10110001 0
b10110001 3
b100000000 2
b10110000 %
b10110000 1
b10110000 :
1&
#1760000
0&
#1765000
b10110001 %
b10110001 1
b10110001 :
b10110001 $
b10110001 0
b10110001 3
b100000000 2
1&
#1770000
0&
#1775000
b10110011 $
b10110011 0
b10110011 3
b100000000 2
b10110010 %
b10110010 1
b10110010 :
1&
#1780000
0&
#1785000
b10110011 %
b10110011 1
b10110011 :
b10110011 $
b10110011 0
b10110011 3
b100000000 2
1&
#1790000
0&
#1795000
b10110101 $
b10110101 0
b10110101 3
b100000000 2
b10110100 %
b10110100 1
b10110100 :
1&
#1800000
0&
#1805000
b10110101 %
b10110101 1
b10110101 :
b10110101 $
b10110101 0
b10110101 3
b100000000 2
1&
#1810000
0&
#1815000
b10110111 $
b10110111 0
b10110111 3
b100000000 2
b10110110 %
b10110110 1
b10110110 :
1&
#1820000
0&
#1825000
b10110111 %
b10110111 1
b10110111 :
b10110111 $
b10110111 0
b10110111 3
b100000000 2
1&
#1830000
0&
#1835000
b10111001 $
b10111001 0
b10111001 3
b100000000 2
b10111000 %
b10111000 1
b10111000 :
1&
#1840000
0&
